{"generationDate": "2015-11-13T16:08:21Z", "antennas": [{"outOfServiceWindows": [{"reason": "PLANNED_MAINTENANCE", "stopTime": "2015-10-15T12:00:00Z", "startTime": "2015-10-15T00:00:00Z"}, {"reason": "PLANNED_MAINTENANCE", "stopTime": "2015-10-17T12:00:00Z", "startTime": "2015-10-17T00:00:00Z"}], "antennaId": "FBX-1"}, {"outOfServiceWindows": [{"reason": "PLANNED_MAINTENANCE", "stopTime": "2015-10-18T12:00:00Z", "startTime": "2015-10-18T00:00:00Z"}, {"reason": "PLANNED_MAINTENANCE", "stopTime": "2015-10-20T12:00:00Z", "startTime": "2015-10-20T00:00:00Z"}], "antennaId": "FBX-2"}]}